{"id":"3","name":"Amazonas","uf":"AM","cities":"[{\"id\":\"219\",\"name\":\"Alvarães\",\"idState\":\"3\"},{\"id\":\"220\",\"name\":\"Amaturá\",\"idState\":\"3\"},{\"id\":\"221\",\"name\":\"Anamã\",\"idState\":\"3\"},{\"id\":\"222\",\"name\":\"Anori\",\"idState\":\"3\"},{\"id\":\"223\",\"name\":\"Apuí\",\"idState\":\"3\"},{\"id\":\"224\",\"name\":\"Atalaia do Norte\",\"idState\":\"3\"},{\"id\":\"225\",\"name\":\"Autazes\",\"idState\":\"3\"},{\"id\":\"226\",\"name\":\"Barcelos\",\"idState\":\"3\"},{\"id\":\"227\",\"name\":\"Barreirinha\",\"idState\":\"3\"},{\"id\":\"228\",\"name\":\"Benjamin Constant\",\"idState\":\"3\"},{\"id\":\"229\",\"name\":\"Beruri\",\"idState\":\"3\"},{\"id\":\"230\",\"name\":\"Boa Vista do Ramos\",\"idState\":\"3\"},{\"id\":\"231\",\"name\":\"Boca do Acre\",\"idState\":\"3\"},{\"id\":\"232\",\"name\":\"Borba\",\"idState\":\"3\"},{\"id\":\"233\",\"name\":\"Caapiranga\",\"idState\":\"3\"},{\"id\":\"234\",\"name\":\"Canutama\",\"idState\":\"3\"},{\"id\":\"235\",\"name\":\"Carauari\",\"idState\":\"3\"},{\"id\":\"236\",\"name\":\"Careiro\",\"idState\":\"3\"},{\"id\":\"237\",\"name\":\"Careiro da Várzea\",\"idState\":\"3\"},{\"id\":\"238\",\"name\":\"Coari\",\"idState\":\"3\"},{\"id\":\"239\",\"name\":\"Codajás\",\"idState\":\"3\"},{\"id\":\"240\",\"name\":\"Eirunepé\",\"idState\":\"3\"},{\"id\":\"241\",\"name\":\"Envira\",\"idState\":\"3\"},{\"id\":\"242\",\"name\":\"Fonte Boa\",\"idState\":\"3\"},{\"id\":\"243\",\"name\":\"Guajará\",\"idState\":\"3\"},{\"id\":\"244\",\"name\":\"Humaitá\",\"idState\":\"3\"},{\"id\":\"245\",\"name\":\"Ipixuna\",\"idState\":\"3\"},{\"id\":\"246\",\"name\":\"Iranduba\",\"idState\":\"3\"},{\"id\":\"247\",\"name\":\"Itacoatiara\",\"idState\":\"3\"},{\"id\":\"248\",\"name\":\"Itamarati\",\"idState\":\"3\"},{\"id\":\"249\",\"name\":\"Itapiranga\",\"idState\":\"3\"},{\"id\":\"250\",\"name\":\"Japurá\",\"idState\":\"3\"},{\"id\":\"251\",\"name\":\"Juruá\",\"idState\":\"3\"},{\"id\":\"252\",\"name\":\"Jutaí\",\"idState\":\"3\"},{\"id\":\"253\",\"name\":\"Lábrea\",\"idState\":\"3\"},{\"id\":\"254\",\"name\":\"Manacapuru\",\"idState\":\"3\"},{\"id\":\"255\",\"name\":\"Manaquiri\",\"idState\":\"3\"},{\"id\":\"256\",\"name\":\"Manaus\",\"idState\":\"3\"},{\"id\":\"257\",\"name\":\"Manicoré\",\"idState\":\"3\"},{\"id\":\"258\",\"name\":\"Maraã\",\"idState\":\"3\"},{\"id\":\"259\",\"name\":\"Maués\",\"idState\":\"3\"},{\"id\":\"260\",\"name\":\"Nhamundá\",\"idState\":\"3\"},{\"id\":\"261\",\"name\":\"Nova Olinda do Norte\",\"idState\":\"3\"},{\"id\":\"262\",\"name\":\"Novo Airão\",\"idState\":\"3\"},{\"id\":\"263\",\"name\":\"Novo Aripuanã\",\"idState\":\"3\"},{\"id\":\"264\",\"name\":\"Parintins\",\"idState\":\"3\"},{\"id\":\"265\",\"name\":\"Pauini\",\"idState\":\"3\"},{\"id\":\"266\",\"name\":\"Presidente Figueiredo\",\"idState\":\"3\"},{\"id\":\"267\",\"name\":\"Rio Preto da Eva\",\"idState\":\"3\"},{\"id\":\"268\",\"name\":\"Santa Isabel do Rio Negro\",\"idState\":\"3\"},{\"id\":\"269\",\"name\":\"Santo Antônio do Içá\",\"idState\":\"3\"},{\"id\":\"270\",\"name\":\"São Gabriel da Cachoeira\",\"idState\":\"3\"},{\"id\":\"271\",\"name\":\"São Paulo de Olivença\",\"idState\":\"3\"},{\"id\":\"272\",\"name\":\"São Sebastião do Uatumã\",\"idState\":\"3\"},{\"id\":\"273\",\"name\":\"Silves\",\"idState\":\"3\"},{\"id\":\"274\",\"name\":\"Tabatinga\",\"idState\":\"3\"},{\"id\":\"275\",\"name\":\"Tapauá\",\"idState\":\"3\"},{\"id\":\"276\",\"name\":\"Tefé\",\"idState\":\"3\"},{\"id\":\"277\",\"name\":\"Tonantins\",\"idState\":\"3\"},{\"id\":\"278\",\"name\":\"Uarini\",\"idState\":\"3\"},{\"id\":\"279\",\"name\":\"Urucará\",\"idState\":\"3\"},{\"id\":\"280\",\"name\":\"Urucurituba\",\"idState\":\"3\"}]"}